xkcd_phrase/__init__.py
xkcd_phrase/xkcd_phrase.py
xkcd_phrase/lib/__init__.py
xkcd_phrase/lib/case.py
xkcd_phrase/lib/xkcd_default.py
xkcd_phrase/lib/xkcd_utilities.py
xkcd_phrase/lib/xkcd_validate.py
xkcd_phrase/lib/__pycache__/__init__.cpython-311.pyc
xkcd_phrase/lib/__pycache__/case.cpython-311.pyc
xkcd_phrase/lib/__pycache__/xkcd_default.cpython-311.pyc
xkcd_phrase/lib/__pycache__/xkcd_utilities.cpython-311.pyc
xkcd_phrase/lib/__pycache__/xkcd_validate.cpython-311.pyc
xkcd_phrase/lib/dictionary/.gitignore
xkcd_phrase/lib/dictionary/eff-long
xkcd_phrase/lib/dictionary/eff-short
xkcd_phrase/lib/dictionary/eff-special
xkcd_phrase-1.0.0.dist-info/LICENSE
xkcd_phrase-1.0.0.dist-info/LICENSE.BSD
xkcd_phrase-1.0.0.dist-info/METADATA
xkcd_phrase-1.0.0.dist-info/WHEEL
xkcd_phrase-1.0.0.dist-info/entry_points.txt
xkcd_phrase-1.0.0.dist-info/top_level.txt
xkcd_phrase-1.0.0.dist-info/RECORD
