Metadata-Version: 2.1
Name: xkcd-phrase
Version: 1.0.0
Summary: Generate secure multiword passphrases, inspired by XKCD
Author-email: Paul Anderson <p.anderson@iinet.net.au>
Project-URL: homepage, https://github.com/pauljosephanderson/xkcd-phrase
Project-URL: repository, https://github.com/pauljosephanderson/xkcd-phrase.git
Project-URL: Bug Tracker, https://github.com/pauljosephanderson/xkcd-phrase/issues
Keywords: xkcd,passphrase
Classifier: Programming Language :: Python
Classifier: Programming Language :: Python :: 3
Classifier: Development Status :: 5 - Production/Stable
Classifier: License :: OSI Approved :: GNU General Public License v3 or later (GPLv3+)
Classifier: License :: OSI Approved :: BSD License
Classifier: Operating System :: OS Independent
Requires-Python: >=3.8
License-File: LICENSE
License-File: LICENSE.BSD
Requires-Dist: argcomplete
